slidingwindow/__init__.py
slidingwindow/window.py
MP_Sliding_Window-0.0.26.dist-info/top_level.txt
MP_Sliding_Window-0.0.26.dist-info/METADATA
MP_Sliding_Window-0.0.26.dist-info/DESCRIPTION.rst
MP_Sliding_Window-0.0.26.dist-info/metadata.json
MP_Sliding_Window-0.0.26.dist-info/WHEEL
MP_Sliding_Window-0.0.26.dist-info/RECORD
