Metadata-Version: 2.0
Name: MP-Sliding-Window
Version: 0.0.26
Summary: Multiprocessing Based Sliding window 
Home-page: UNKNOWN
Author: Jorge Alpedrinha Ramos
Author-email: jalpedrinharamos@gmail.com
License: LICENSE.txt
Platform: UNKNOWN
